TracGoogleMapMacro-0.6.dist-info/METADATA
TracGoogleMapMacro-0.6.dist-info/RECORD
TracGoogleMapMacro-0.6.dist-info/WHEEL
TracGoogleMapMacro-0.6.dist-info/entry_points.txt
TracGoogleMapMacro-0.6.dist-info/top_level.txt
tracgooglemap/__init__.py
tracgooglemap/macro.py
tracgooglemap/htdocs/tracgooglemap.css
tracgooglemap/htdocs/tracgooglemap.js
